dj_log_config_helper.py
dj_log_config_helper-0.2.3.dist-info/top_level.txt
dj_log_config_helper-0.2.3.dist-info/METADATA
dj_log_config_helper-0.2.3.dist-info/DESCRIPTION.rst
dj_log_config_helper-0.2.3.dist-info/metadata.json
dj_log_config_helper-0.2.3.dist-info/WHEEL
dj_log_config_helper-0.2.3.dist-info/RECORD
