Metadata-Version: 2.0
Name: dj-log-config-helper
Version: 0.2.3
Summary: Simplify log configuration across Django projects
Home-page: https://github.com/Harvard-University-iCommons/dj-log-config-helper
Author: Jaime Bermudez
Author-email: jaime_bermudez@harvard.edu
License: The MIT License (MIT)
Requires-Dist: django
